[
    {
        "id": "1",
        "title": "Booki",
        "picture":"../assets/booki.jpg"
    },
    {      
        "id": "2",
        "title": "Sophie Bluel",
        "picture":"../assets/sophie-bluel.png"
    },
    {
        "id": "3",
        "title": "Nina Carducci",
        "picture": "../assets/nina-carducci.png"
    },
    {
        "id": "4",
        "title": "Kasa",
        "picture": "../assets/kasa.jpg"
    },
    {
        "id": "5",
        "title": "Mon Vieux Grimmoire",
        "picture": "../assets/mon-vieux-grimmoire.jpg"
    }
    ]